textware/__init__.py
textware/core/__init__.py
textware/core/batching/batchmaker.py
textware/core/counting/counter.py
textware/core/counting/nested_counter.py
textware/core/transprocessing/base_processor.py
textware/core/transprocessing/cleaner.py
textware/core/transprocessing/piecemaker.py
textware/core/utils/__init__.py
textware/core/utils/dummywriter.py
textware/core/utils/hashing.py
textware/pipe/__init__.py
textware/pipe/distr/association.py
textware/pipe/distr/markov.py
textware/pipe/distr/stream.py
textware-0.0.12.dist-info/METADATA
textware-0.0.12.dist-info/WHEEL
textware-0.0.12.dist-info/RECORD
