Metadata-Version: 2.1
Name: textware
Version: 0.0.12
Summary: All tools about text
Author: Kun Lu
Author-email: hi@shugic.com
Requires-Python: >=3.10,<4.0
Classifier: Programming Language :: Python :: 3
Classifier: Programming Language :: Python :: 3.10
Classifier: Programming Language :: Python :: 3.11
Classifier: Programming Language :: Python :: 3.12
Requires-Dist: numpy
Requires-Dist: pydantic
